{
  "id": "1521018",
  "name": "博客",
  "font_family": "iconfont",
  "css_prefix_text": "icon-",
  "description": "",
  "glyphs": [
    {
      "icon_id": "808581",
      "name": "h5",
      "font_class": "h5",
      "unicode": "e633",
      "unicode_decimal": 58931
    },
    {
      "icon_id": "929458",
      "name": "home",
      "font_class": "home1",
      "unicode": "e734",
      "unicode_decimal": 59188
    },
    {
      "icon_id": "1084694",
      "name": "home",
      "font_class": "home",
      "unicode": "e65e",
      "unicode_decimal": 58974
    },
    {
      "icon_id": "2493970",
      "name": "prog-golang02",
      "font_class": "prog-golang",
      "unicode": "e667",
      "unicode_decimal": 58983
    },
    {
      "icon_id": "2493971",
      "name": "prog-golang01",
      "font_class": "prog-golang1",
      "unicode": "e668",
      "unicode_decimal": 58984
    },
    {
      "icon_id": "4667135",
      "name": "Golang",
      "font_class": "Golang",
      "unicode": "e600",
      "unicode_decimal": 58880
    },
    {
      "icon_id": "4667136",
      "name": "Golang",
      "font_class": "Golang1",
      "unicode": "e601",
      "unicode_decimal": 58881
    },
    {
      "icon_id": "6926775",
      "name": "golang",
      "font_class": "golang",
      "unicode": "e612",
      "unicode_decimal": 58898
    },
    {
      "icon_id": "6926777",
      "name": "golang",
      "font_class": "golang1",
      "unicode": "e607",
      "unicode_decimal": 58887
    },
    {
      "icon_id": "11180531",
      "name": "golang",
      "font_class": "go",
      "unicode": "e608",
      "unicode_decimal": 58888
    },
    {
      "icon_id": "11180532",
      "name": "golang-waitou",
      "font_class": "go2",
      "unicode": "e60a",
      "unicode_decimal": 58890
    }
  ]
}
